[
  {
    "key": "ctrl+cmd+p",
    "command": "projectManager.listProjects"
  },
  {
    "key": "alt+cmd+p",
    "command": "-projectManager.listProjects"
  },
  {
    "key": "ctrl+shift+t",
    "command": "todohighlight.listAnnotations"
  },
  {
    "key": "cmd+y",
    "command": "redo",
    "when": "textInputFocus && !editorReadonly"
  },
  {
    "key": "shift+cmd+z",
    "command": "-redo",
    "when": "textInputFocus && !editorReadonly"
  },
  {
    "key": "cmd+y",
    "command": "editor.action.webvieweditor.redo",
    "when": "!editorFocus && !inputFocus && !webviewHasOwnEditFunctions && activeEditor == 'WebviewEditor'"
  },
  {
    "key": "shift+cmd+z",
    "command": "-editor.action.webvieweditor.redo",
    "when": "!editorFocus && !inputFocus && !webviewHasOwnEditFunctions && activeEditor == 'WebviewEditor'"
  },
  {
    "key": "cmd+y",
    "command": "editor.action.customEditor.redo",
    "when": "focusedCustomEditorIsEditable && !inputFocus"
  },
  {
    "key": "shift+cmd+z",
    "command": "-editor.action.customEditor.redo",
    "when": "focusedCustomEditorIsEditable && !inputFocus"
  },
  {
    "key": "shift+a",
    "command": "explorer.newFolder",
    "when": "explorerViewletVisible && filesExplorerFocus && !explorerResourceReadonly && !inputFocus"
  },
  {
    "key": "cmd+a",
    "command": "explorer.newFile",
    "when": "explorerViewletVisible && filesExplorerFocus && !explorerResourceReadonly && !inputFocus"
  }
]
